markdown_doc/__init__.py
markdown_doc/__main__.py
markdown_doc/argparse_action.py
markdown_doc/formatter.py
markdown_doc/generator.py
markdown_doc/import_util.py
markdown_doc/py.typed
markdown_doc/resolver.py
markdown_doc-0.1.7.dist-info/licenses/LICENSE
markdown_doc-0.1.7.dist-info/METADATA
markdown_doc-0.1.7.dist-info/WHEEL
markdown_doc-0.1.7.dist-info/top_level.txt
markdown_doc-0.1.7.dist-info/zip-safe
markdown_doc-0.1.7.dist-info/RECORD
