Metadata-Version: 2.4
Name: markdown-doc
Version: 0.1.7
Summary: Generate Markdown documentation from Python code
Author-email: Levente Hunyadi <hunyadi@gmail.com>
Maintainer-email: Levente Hunyadi <hunyadi@gmail.com>
License-Expression: MIT
Project-URL: Homepage, https://github.com/hunyadi/markdown_doc
Project-URL: Source, https://github.com/hunyadi/markdown_doc
Keywords: markdown,documentation-generator,python-typing
Classifier: Development Status :: 5 - Production/Stable
Classifier: Environment :: Console
Classifier: Intended Audience :: Developers
Classifier: Intended Audience :: End Users/Desktop
Classifier: Operating System :: OS Independent
Classifier: Programming Language :: Python :: 3
Classifier: Programming Language :: Python :: 3.10
Classifier: Programming Language :: Python :: 3.11
Classifier: Programming Language :: Python :: 3.12
Classifier: Programming Language :: Python :: 3.13
Classifier: Programming Language :: Python :: 3.14
Classifier: Programming Language :: Python :: 3 :: Only
Classifier: Topic :: Documentation
Classifier: Topic :: Text Processing :: Markup :: Markdown
Classifier: Topic :: Utilities
Classifier: Typing :: Typed
Requires-Python: >=3.10
License-File: LICENSE
Requires-Dist: docsource>=0.1
Provides-Extra: dev
Requires-Dist: build>=1.3; extra == "dev"
Requires-Dist: mypy>=1.18; extra == "dev"
Requires-Dist: ruff>=0.14; extra == "dev"
Dynamic: license-file
